hdcms_helper/.DS_Store
hdcms_helper/__init__.py
hdcms_helper/clean.py
hdcms_helper/gen.py
hdcms_helper/stats.py
hdcms_helper/visualize.py
hdcms_helper-0.1.8.dist-info/METADATA
hdcms_helper-0.1.8.dist-info/WHEEL
hdcms_helper-0.1.8.dist-info/licenses/LICENSE.txt
hdcms_helper-0.1.8.dist-info/RECORD
