Metadata-Version: 2.1
Name: hdcms-helper
Version: 0.1.8
Summary: This package creates useful helper functions for python API
Project-URL: Homepage, https://github.com/jasoneveleth/pyhdcms-helper
Project-URL: Bug Tracker, https://github.com/jasoneveleth/pyhdcms-helper/issues
Author: Arun Moorthy
Author-email: Jason Eveleth <hdcms-helper@jasoneveleth.com>
License: NIST-developed software is provided by NIST as a public service. You may use,
License-File: LICENSE.txt
Requires-Python: >=3.7
Requires-Dist: hdcms
Requires-Dist: matplotlib
Requires-Dist: numpy
Requires-Dist: opencv-python
Requires-Dist: scipy
